KratosMultiphysics/GeoMechanicsApplication/__init__.py
KratosMultiphysics/GeoMechanicsApplication/apply_c_phi_reduction_process.py
KratosMultiphysics/GeoMechanicsApplication/apply_excavation_process.py
KratosMultiphysics/GeoMechanicsApplication/apply_final_stresses_of_previous_stage_to_initial_state.py
KratosMultiphysics/GeoMechanicsApplication/apply_initial_uniform_stress_field.py
KratosMultiphysics/GeoMechanicsApplication/apply_k0_procedure_process.py
KratosMultiphysics/GeoMechanicsApplication/apply_normal_load_table_process.py
KratosMultiphysics/GeoMechanicsApplication/apply_scalar_constraint_table_process.py
KratosMultiphysics/GeoMechanicsApplication/apply_vector_constraint_table_process.py
KratosMultiphysics/GeoMechanicsApplication/apply_write_result_vector_process.py
KratosMultiphysics/GeoMechanicsApplication/check_and_prepare_model_process_geo.py
KratosMultiphysics/GeoMechanicsApplication/collect_stages.py
KratosMultiphysics/GeoMechanicsApplication/context_managers.py
KratosMultiphysics/GeoMechanicsApplication/find_neighbours_of_interfaces_process.py
KratosMultiphysics/GeoMechanicsApplication/gap_closure_interface_activation_process.py
KratosMultiphysics/GeoMechanicsApplication/geo_extrapolate_integration_point_values_to_nodes_process.py
KratosMultiphysics/GeoMechanicsApplication/geo_mechanics_analysis.py
KratosMultiphysics/GeoMechanicsApplication/geo_plot_utilities.py
KratosMultiphysics/GeoMechanicsApplication/geomechanics_Pw_solver.py
KratosMultiphysics/GeoMechanicsApplication/geomechanics_T_solver.py
KratosMultiphysics/GeoMechanicsApplication/geomechanics_U_Pw_solver.py
KratosMultiphysics/GeoMechanicsApplication/geomechanics_analysis.py
KratosMultiphysics/GeoMechanicsApplication/geomechanics_cleaning_utility.py
KratosMultiphysics/GeoMechanicsApplication/geomechanics_solver.py
KratosMultiphysics/GeoMechanicsApplication/geomechanics_solvers_wrapper.py
KratosMultiphysics/GeoMechanicsApplication/gid_output_file_reader.py
kratosgeomechanicsapplication-10.4.0.dist-info/METADATA
kratosgeomechanicsapplication-10.4.0.dist-info/WHEEL
kratosgeomechanicsapplication-10.4.0.dist-info/RECORD
